pytest_dbt_duckdb/__init__.py
pytest_dbt_duckdb/connector.py
pytest_dbt_duckdb/dbt_executor.py
pytest_dbt_duckdb/dbt_validator.py
pytest_dbt_duckdb/plugin.py
pytest_dbt_duckdb/snowflake_functions.py
pytest_dbt_duckdb/sql_methods.py
pytest_dbt_duckdb-0.1.15.dist-info/METADATA
pytest_dbt_duckdb-0.1.15.dist-info/WHEEL
pytest_dbt_duckdb-0.1.15.dist-info/entry_points.txt
pytest_dbt_duckdb-0.1.15.dist-info/licenses/LICENSE
pytest_dbt_duckdb-0.1.15.dist-info/RECORD
