Metadata-Version: 2.4
Name: pytest-dbt-duckdb
Version: 0.1.15
Summary: Fearless testing for dbt models, powered by DuckDB.
License-File: LICENSE
Classifier: Development Status :: 4 - Beta
Classifier: Framework :: Pytest
Classifier: Intended Audience :: Developers
Classifier: Intended Audience :: Information Technology
Classifier: Intended Audience :: Science/Research
Classifier: Programming Language :: Python :: 3.11
Classifier: Programming Language :: Python :: 3.12
Classifier: Topic :: Database
Classifier: Topic :: Scientific/Engineering :: Information Analysis
Classifier: Topic :: Software Development :: Testing
Requires-Python: >=3.11
Requires-Dist: absl-py>=2.1.0
Requires-Dist: dbt-duckdb>=1.9.1
Requires-Dist: duckdb==1.2.2
Requires-Dist: numpy>=2.2.2
Requires-Dist: pandas>=2.2.3
Requires-Dist: pyarrow>=19.0.0
Requires-Dist: pydantic-settings>=2.7.1
Requires-Dist: pytest-env>=1.1.5
Requires-Dist: pytest>=8.3.4
Requires-Dist: ruamel-yaml>=0.18.10
